{"v":5,"entries":{"home--docs":{"id":"home--docs","title":"Home","name":"Docs","importPath":"./src/stories.mdx","storiesImports":[],"type":"docs","tags":["dev","test","autodocs","unattached-mdx"]},"commons-button--docs":{"id":"commons-button--docs","title":"commons/Button","name":"Docs","importPath":"./src/components/Button/stories.tsx","type":"docs","tags":["dev","test","autodocs"],"storiesImports":[]},"commons-button--basic":{"type":"story","id":"commons-button--basic","name":"Basic","title":"commons/Button","importPath":"./src/components/Button/stories.tsx","componentPath":"@prismal/react-native","tags":["dev","test","autodocs"]},"commons-card--docs":{"id":"commons-card--docs","title":"Commons/Card","name":"Docs","importPath":"./src/components/Card/stories.tsx","type":"docs","tags":["dev","test","autodocs"],"storiesImports":[]},"commons-card--basic":{"type":"story","id":"commons-card--basic","name":"Basic","title":"Commons/Card","importPath":"./src/components/Card/stories.tsx","componentPath":"@prismal/react-native","tags":["dev","test","autodocs"]},"commons-tabs--docs":{"id":"commons-tabs--docs","title":"Commons/Tabs","name":"Docs","importPath":"./src/components/Tabs/stories.tsx","type":"docs","tags":["dev","test","autodocs"],"storiesImports":[]},"commons-tabs--basic":{"type":"story","id":"commons-tabs--basic","name":"Basic","title":"Commons/Tabs","importPath":"./src/components/Tabs/stories.tsx","componentPath":"@prismal/react-native","tags":["dev","test","autodocs"]}}}